rolab_tb/__init__.py
rolab_tb/log.py
rolab_tb/turtlebot.py
rolab_tb/__pycache__/__init__.cpython-38.pyc
rolab_tb/__pycache__/log.cpython-38.pyc
rolab_tb/__pycache__/turtlebot.cpython-38.pyc
rolab_tb/msgs/archive/cmd_vel.json
rolab_tb/msgs/archive/cmd_vel.json.license
rolab_tb/msgs/pub/cmd_vel.json
rolab_tb/msgs/pub/cmd_vel.json.license
rolab_tb/msgs/sub/imu.json
rolab_tb/msgs/sub/imu.json.license
rolab_tb/msgs/sub/odom.json
rolab_tb/msgs/sub/odom.json.license
rolab_tb/msgs/sub/scan.json
rolab_tb/msgs/sub/scan.json.license
rolab_tb/msgs/sub/sensor_state.json
rolab_tb/msgs/sub/sensor_state.json.license
rolab_tb/sensortests/__init__.py
rolab_tb/sensortests/encoders.py
rolab_tb/sensortests/__pycache__/__init__.cpython-38.pyc
rolab_tb/sensortests/__pycache__/encoders.cpython-38.pyc
rolab_tb/sensortests/benchmarks/__init__.py
rolab_tb/sensortests/benchmarks/encoders_linvel_step_022_t3.csv
rolab_tb/sensortests/benchmarks/encoders_linvel_step_theory.csv
rolab_tb-0.0.6.4.dist-info/METADATA
rolab_tb-0.0.6.4.dist-info/WHEEL
rolab_tb-0.0.6.4.dist-info/top_level.txt
rolab_tb-0.0.6.4.dist-info/RECORD
