Metadata-Version: 2.1
Name: rolab-tb
Version: 0.0.6.4
Summary: Lightweight ROS-less API for Turtlebots, over a websocket bridge
Author: Senne Van Baelen
Author-email: senne.vanbaelen@kuleuven.be
License: UNKNOWN
Platform: UNKNOWN
Classifier: Programming Language :: Python :: 3
Classifier: License :: OSI Approved :: Apache Software License
Classifier: Operating System :: OS Independent
Requires-Python: >=3.6
Requires-Dist: numpy
Requires-Dist: websockets
